[
  {
    "rating_range": "1000-1100",
    "correctness": "bad",
    "speed": "fast",
    "count": 3
  },
  {
    "rating_range": "1000-1100",
    "correctness": "bad",
    "speed": "slow",
    "count": 2
  },
  {
    "rating_range": "1000-1100",
    "correctness": "good",
    "speed": "fast",
    "count": 47
  },
  {
    "rating_range": "1000-1100",
    "correctness": "good",
    "speed": "slow",
    "count": 17
  },
  {
    "rating_range": "1100-1200",
    "correctness": "bad",
    "speed": "fast",
    "count": 3
  },
  {
    "rating_range": "1100-1200",
    "correctness": "bad",
    "speed": "slow",
    "count": 3
  },
  {
    "rating_range": "1100-1200",
    "correctness": "good",
    "speed": "fast",
    "count": 39
  },
  {
    "rating_range": "1100-1200",
    "correctness": "good",
    "speed": "slow",
    "count": 26
  },
  {
    "rating_range": "1200-1300",
    "correctness": "bad",
    "speed": "fast",
    "count": 5
  },
  {
    "rating_range": "1200-1300",
    "correctness": "bad",
    "speed": "slow",
    "count": 2
  },
  {
    "rating_range": "1200-1300",
    "correctness": "good",
    "speed": "fast",
    "count": 12
  },
  {
    "rating_range": "1200-1300",
    "correctness": "good",
    "speed": "slow",
    "count": 14
  },
  {
    "rating_range": "1300-1400",
    "correctness": "bad",
    "speed": "fast",
    "count": 9
  },
  {
    "rating_range": "1300-1400",
    "correctness": "bad",
    "speed": "slow",
    "count": 2
  },
  {
    "rating_range": "1300-1400",
    "correctness": "good",
    "speed": "fast",
    "count": 16
  },
  {
    "rating_range": "1300-1400",
    "correctness": "good",
    "speed": "slow",
    "count": 20
  },
  {
    "rating_range": "1400-1500",
    "correctness": "bad",
    "speed": "fast",
    "count": 8
  },
  {
    "rating_range": "1400-1500",
    "correctness": "bad",
    "speed": "slow",
    "count": 5
  },
  {
    "rating_range": "1400-1500",
    "correctness": "good",
    "speed": "fast",
    "count": 9
  },
  {
    "rating_range": "1400-1500",
    "correctness": "good",
    "speed": "slow",
    "count": 10
  },
  {
    "rating_range": "1500-1600",
    "correctness": "bad",
    "speed": "slow",
    "count": 1
  }
]
